HISTORY.md
MANIFEST.in
README.rst
setup.py
django_wechat_web/__init__.py
django_wechat_web/admin.py
django_wechat_web/apps.py
django_wechat_web/exception.py
django_wechat_web/models.py
django_wechat_web/response.py
django_wechat_web/tests.py
django_wechat_web/urls.py
django_wechat_web/views.py
django_wechat_web/wechat.py
django_wechat_web.egg-info/PKG-INFO
django_wechat_web.egg-info/SOURCES.txt
django_wechat_web.egg-info/dependency_links.txt
django_wechat_web.egg-info/requires.txt
django_wechat_web.egg-info/top_level.txt
django_wechat_web/migrations/0001_initial.py
django_wechat_web/migrations/__init__.py